tree_sitter_bosque/__init__.pyi
tree_sitter_bosque/binding.c
tree_sitter_bosque/__init__.py
tree_sitter_bosque/py.typed
tree_sitter_bosque/_binding.abi3.so
tree_sitter_bosque/queries/highlights.scm
tree_sitter_bosque/queries/injections.scm
tree_sitter_bosque-0.1.5.dist-info/RECORD
tree_sitter_bosque-0.1.5.dist-info/WHEEL
tree_sitter_bosque-0.1.5.dist-info/top_level.txt
tree_sitter_bosque-0.1.5.dist-info/METADATA
