Metadata-Version: 2.4
Name: tree-sitter-bosque
Version: 0.1.5
Summary: n/a
Author-email: Kennett Puerto <kennettdev1@gmail.com>
License: MIT
Project-URL: Homepage, https://github.com/karidus-423/tree-sitter-bosque
Keywords: incremental,parsing,tree-sitter,bosque
Classifier: Intended Audience :: Developers
Classifier: Topic :: Software Development :: Compilers
Classifier: Topic :: Text Processing :: Linguistic
Classifier: Typing :: Typed
Requires-Python: >=3.10
Provides-Extra: core
Requires-Dist: tree-sitter~=0.24; extra == "core"
